innova_controls/airleaf.py
innova_controls/constants.py
innova_controls/fan_speed.py
innova_controls/innova.py
innova_controls/innova_device.py
innova_controls/innova_factory.py
innova_controls/mode.py
innova_controls/network_functions.py
innova_controls/twopointzero.py
innova_controls-2.2.3.dist-info/LICENSE
innova_controls-2.2.3.dist-info/METADATA
innova_controls-2.2.3.dist-info/WHEEL
innova_controls-2.2.3.dist-info/top_level.txt
innova_controls-2.2.3.dist-info/RECORD
