Metadata-Version: 2.1
Name: innova-controls
Version: 2.2.3
Summary: Innova Air Conditioner Control API
Home-page: https://github.com/danielrivard/innova-controls
Author: Daniel Rivard
License: Apache
Project-URL: Bug Reports, https://github.com/danielrivard/innova-controls/issues
Project-URL: Source, https://github.com/danielrivard/innova-controls/
Keywords: development,home automation,library,innova
Classifier: Development Status :: 4 - Beta
Classifier: Intended Audience :: Developers
Classifier: Topic :: Internet :: WWW/HTTP
Classifier: Topic :: Software Development :: Libraries
Classifier: License :: OSI Approved :: Apache Software License
Classifier: Natural Language :: English
Classifier: Programming Language :: Python :: 3
Requires-Python: >=3.9, <4
License-File: LICENSE
Requires-Dist: aiohttp<4.0.0,>=3.0.0
Requires-Dist: retry2>=0.9.5
